{
    "id": 2004239,
    "home_team_score": 0,
    "away_team_score": 4,
    "date_time": "2025-02-22T06:00:00Z",
    "stadium": {
        "id": 1484,
        "name": "Central Coast Stadium",
        "city": "Gosford",
        "capacity": 20119
    },
    "home_team": {
        "id": 870,
        "name": "Central Coast Mariners Football Club",
        "short_name": "CC Mariners",
        "acronym": "CCM"
    },
    "home_team_kit": {
        "id": 1024,
        "team_id": 870,
        "season": {
            "id": 3,
            "start_year": 2016,
            "end_year": 2017,
            "name": "2016/2017"
        },
        "name": "Home",
        "jersey_color": "#f9db0d",
        "number_color": "#000000"
    },
    "away_team": {
        "id": 2902,
        "name": "Western Sydney Wanderers FC",
        "short_name": "Western Sydney",
        "acronym": "WES"
    },
    "away_team_kit": {
        "id": 15779,
        "team_id": 2902,
        "season": {
            "id": 95,
            "start_year": 2024,
            "end_year": 2025,
            "name": "2024/2025"
        },
        "name": "away",
        "jersey_color": "#216D04",
        "number_color": "#FFFFFF"
    },
    "home_team_coach": null,
    "away_team_coach": null,
    "home_team_playing_time": {
        "minutes_tip": 25.04,
        "minutes_otip": 25.53
    },
    "away_team_playing_time": {
        "minutes_tip": 25.53,
        "minutes_otip": 25.04
    },
    "competition_edition": {
        "id": 870,
        "competition": {
            "id": 61,
            "area": "AUS",
            "name": "A-League",
            "gender": "male",
            "age_group": "adult"
        },
        "season": {
            "id": 95,
            "start_year": 2024,
            "end_year": 2025,
            "name": "2024/2025"
        },
        "name": "AUS - A-League - 2024/2025"
    },
    "match_periods": [
        {
            "period": 1,
            "name": "period_1",
            "start_frame": 10,
            "end_frame": 28900,
            "duration_frames": 28890,
            "duration_minutes": 48.15
        },
        {
            "period": 2,
            "name": "period_2",
            "start_frame": 28910,
            "end_frame": 58400,
            "duration_frames": 29490,
            "duration_minutes": 49.15
        }
    ],
    "competition_round": {
        "id": 625,
        "name": "Round 20",
        "round_number": 20,
        "potential_overtime": false
    },
    "referees": [],
    "players": [
        {
            "player_role": {
                "id": 13,
                "position_group": "Wide Attacker",
                "name": "Right Winger",
                "acronym": "RW"
            },
            "start_time": "00:00:00",
            "end_time": "00:52:10",
            "number": 15,
            "yellow_card": 0,
            "red_card": 0,
            "injured": false,
            "goal": 0,
            "own_goal": 0,
            "playing_time": {
                "total": {
                    "minutes_tip": 14.86,
                    "minutes_otip": 14.2,
                    "start_frame": 10,
                    "end_frame": 33209,
                    "minutes_played": 55.32,
                    "minutes_played_regular_time": 55.32
                },
                "by_period": [
                    {
                        "name": "period_1",
                        "minutes_tip": 13.76,
                        "minutes_otip": 12.34,
                        "start_frame": 10,
                        "end_frame": 28900,
                        "minutes_played": 48.15
                    },
                    {
                        "name": "period_2",
                        "minutes_tip": 1.1,
                        "minutes_otip": 1.86,
                        "start_frame": 28910,
                        "end_frame": 33209,
                        "minutes_played": 7.16
                    }
                ]
            },
            "team_player_id": 21891,
            "team_id": 870,
            "id": 23930,
            "first_name": "Storm ",
            "last_name": "Roux",
            "short_name": "S. Roux",
            "birthday": "1993-01-13",
            "trackable_object": 24888,
            "gender": "male"
        },
        {
            "player_role": {
                "id": 13,
                "position_group": "Wide Attacker",
                "name": "Right Winger",
                "acronym": "RW"
            },
            "start_time": "00:48:09",
            "end_time": null,
            "number": 21,
            "yellow_card": 0,
            "red_card": 0,
            "injured": false,
            "goal": 0,
            "own_goal": 0,
            "playing_time": {
                "total": {
                    "minutes_tip": 11.28,
                    "minutes_otip": 13.19,
                    "start_frame": 28910,
                    "end_frame": 58399,
                    "minutes_played": 49.15,
                    "minutes_played_regular_time": 49.15
                },
                "by_period": [
                    {
                        "name": "period_2",
                        "minutes_tip": 11.28,
                        "minutes_otip": 13.19,
                        "start_frame": 28910,
                        "end_frame": 58399,
                        "minutes_played": 49.15
                    }
                ]
            },
            "team_player_id": 1554900,
            "team_id": 870,
            "id": 966114,
            "first_name": "Abdelelah",
            "last_name": "Faisal",
            "short_name": "A. Faisal",
            "birthday": "2005-10-27",
            "trackable_object": 967677,
            "gender": "male"
        },
        {
            "player_role": {
                "id": 19,
                "position_group": "Full Back",
                "name": "Left Back",
                "acronym": "LB"
            },
            "start_time": "00:00:00",
            "end_time": "01:27:49",
            "number": 19,
            "yellow_card": 0,
            "red_card": 0,
            "injured": false,
            "goal": 1,
            "own_goal": 0,
            "playing_time": {
                "total": {
                    "minutes_tip": 23.36,
                    "minutes_otip": 23.48,
                    "start_frame": 10,
                    "end_frame": 54599,
                    "minutes_played": 90.96,
                    "minutes_played_regular_time": 90.96
                },
                "by_period": [
                    {
                        "name": "period_1",
                        "minutes_tip": 12.34,
                        "minutes_otip": 13.76,
                        "start_frame": 10,
                        "end_frame": 28900,
                        "minutes_played": 48.15
                    },
                    {
                        "name": "period_2",
                        "minutes_tip": 11.02,
                        "minutes_otip": 9.72,
                        "start_frame": 28910,
                        "end_frame": 54599,
                        "minutes_played": 42.82
                    }
                ]
            },
            "team_player_id": 1204899,
            "team_id": 2902,
            "id": 51664,
            "first_name": "Jack",
            "last_name": "Clisby",
            "short_name": "J. Clisby",
            "birthday": "1992-02-16",
            "trackable_object": 52790,
            "gender": "male"
        },
        {
            "player_role": {
                "id": 10,
                "position_group": "Midfield",
                "name": "Right Midfield",
                "acronym": "RM"
            },
            "start_time": "00:00:00",
            "end_time": "00:48:09",
            "number": 36,
            "yellow_card": 0,
            "red_card": 0,
            "injured": false,
            "goal": 0,
            "own_goal": 0,
            "playing_time": {
                "total": {
                    "minutes_tip": 13.76,
                    "minutes_otip": 12.34,
                    "start_frame": 10,
                    "end_frame": 28899,
                    "minutes_played": 48.15,
                    "minutes_played_regular_time": 48.15
                },
                "by_period": [
                    {
                        "name": "period_1",
                        "minutes_tip": 13.76,
                        "minutes_otip": 12.34,
                        "start_frame": 10,
                        "end_frame": 28899,
                        "minutes_played": 48.15
                    }
                ]
            },
            "team_player_id": 1448859,
            "team_id": 870,
            "id": 923864,
            "first_name": "Haine Anthony",
            "last_name": "Eames",
            "short_name": "H. Eames",
            "birthday": "2008-02-27",
            "trackable_object": 925427,
            "gender": "male"
        },
        {
            "player_role": {
                "id": 9,
                "position_group": "Midfield",
                "name": "Left Midfield",
                "acronym": "LM"
            },
            "start_time": "00:00:00",
            "end_time": null,
            "number": 16,
            "yellow_card": 0,
            "red_card": 0,
            "injured": false,
            "goal": 0,
            "own_goal": 0,
            "playing_time": {
                "total": {
                    "minutes_tip": 25.04,
                    "minutes_otip": 25.53,
                    "start_frame": 10,
                    "end_frame": 58399,
                    "minutes_played": 97.3,
                    "minutes_played_regular_time": 97.3
                },
                "by_period": [
                    {
                        "name": "period_1",
                        "minutes_tip": 13.76,
                        "minutes_otip": 12.34,
                        "start_frame": 10,
                        "end_frame": 28900,
                        "minutes_played": 48.15
                    },
                    {
                        "name": "period_2",
                        "minutes_tip": 11.28,
                        "minutes_otip": 13.19,
                        "start_frame": 28910,
                        "end_frame": 58399,
                        "minutes_played": 49.15
                    }
                ]
            },
            "team_player_id": 1204876,
            "team_id": 870,
            "id": 795508,
            "first_name": "Harrison",
            "last_name": "Steele",
            "short_name": "H. Steele",
            "birthday": "2002-10-12",
            "trackable_object": 797071,
            "gender": "male"
        },
        {
            "player_role": {
                "id": 15,
                "position_group": "Center Forward",
                "name": "Center Forward",
                "acronym": "CF"
            },
            "start_time": "01:27:49",
            "end_time": null,
            "number": 21,
            "yellow_card": 0,
            "red_card": 0,
            "injured": false,
            "goal": 0,
            "own_goal": 0,
            "playing_time": {
                "total": {
                    "minutes_tip": 2.17,
                    "minutes_otip": 1.57,
                    "start_frame": 54600,
                    "end_frame": 58399,
                    "minutes_played": 6.33,
                    "minutes_played_regular_time": 6.33
                },
                "by_period": [
                    {
                        "name": "period_2",
                        "minutes_tip": 2.17,
                        "minutes_otip": 1.57,
                        "start_frame": 54600,
                        "end_frame": 58399,
                        "minutes_played": 6.33
                    }
                ]
            },
            "team_player_id": 1233872,
            "team_id": 2902,
            "id": 809826,
            "first_name": "Aydan Johnathan",
            "last_name": "Hammond ",
            "short_name": "A. Hammond",
            "birthday": "2003-12-23",
            "trackable_object": 811389,
            "gender": "male"
        },
        {
            "player_role": {
                "id": 20,
                "position_group": "Full Back",
                "name": "Right Back",
                "acronym": "RB"
            },
            "start_time": "00:52:10",
            "end_time": null,
            "number": 27,
            "yellow_card": 0,
            "red_card": 0,
            "injured": false,
            "goal": 0,
            "own_goal": 0,
            "playing_time": {
                "total": {
                    "minutes_tip": 10.18,
                    "minutes_otip": 11.33,
                    "start_frame": 33210,
                    "end_frame": 58399,
                    "minutes_played": 41.98,
                    "minutes_played_regular_time": 41.98
                },
                "by_period": [
                    {
                        "name": "period_2",
                        "minutes_tip": 10.18,
                        "minutes_otip": 11.33,
                        "start_frame": 33210,
                        "end_frame": 58399,
                        "minutes_played": 41.98
                    }
                ]
            },
            "team_player_id": 1448858,
            "team_id": 870,
            "id": 923863,
            "first_name": "Sasha",
            "last_name": "Kuzevski",
            "short_name": "S. Kuzevski",
            "birthday": "2001-03-27",
            "trackable_object": 925426,
            "gender": "male"
        },
        {
            "player_role": {
                "id": 12,
                "position_group": "Wide Attacker",
                "name": "Left Winger",
                "acronym": "LW"
            },
            "start_time": "00:48:09",
            "end_time": null,
            "number": 7,
            "yellow_card": 0,
            "red_card": 0,
            "injured": false,
            "goal": 0,
            "own_goal": 0,
            "playing_time": {
                "total": {
                    "minutes_tip": 11.28,
                    "minutes_otip": 13.19,
                    "start_frame": 28910,
                    "end_frame": 58399,
                    "minutes_played": 49.15,
                    "minutes_played_regular_time": 49.15
                },
                "by_period": [
                    {
                        "name": "period_2",
                        "minutes_tip": 11.28,
                        "minutes_otip": 13.19,
                        "start_frame": 28910,
                        "end_frame": 58399,
                        "minutes_played": 49.15
                    }
                ]
            },
            "team_player_id": 1204878,
            "team_id": 870,
            "id": 795509,
            "first_name": "Christian",
            "last_name": "Theoharous",
            "short_name": "C. Theoharous",
            "birthday": "1999-12-06",
            "trackable_object": 797072,
            "gender": "male"
        },
        {
            "player_role": {
                "id": 15,
                "position_group": "Center Forward",
                "name": "Center Forward",
                "acronym": "CF"
            },
            "start_time": "01:04:21",
            "end_time": null,
            "number": 9,
            "yellow_card": 0,
            "red_card": 0,
            "injured": false,
            "goal": 1,
            "own_goal": 0,
            "playing_time": {
                "total": {
                    "minutes_tip": 9.23,
                    "minutes_otip": 7.3,
                    "start_frame": 40520,
                    "end_frame": 58399,
                    "minutes_played": 29.8,
                    "minutes_played_regular_time": 29.8
                },
                "by_period": [
                    {
                        "name": "period_2",
                        "minutes_tip": 9.23,
                        "minutes_otip": 7.3,
                        "start_frame": 40520,
                        "end_frame": 58399,
                        "minutes_played": 29.8
                    }
                ]
            },
            "team_player_id": 1204900,
            "team_id": 2902,
            "id": 13567,
            "first_name": "Marcus",
            "last_name": "Antonsson",
            "short_name": "M. Antonsson",
            "birthday": "1991-05-08",
            "trackable_object": 13764,
            "gender": "male"
        },
        {
            "player_role": {
                "id": 10,
                "position_group": "Midfield",
                "name": "Right Midfield",
                "acronym": "RM"
            },
            "start_time": "00:00:00",
            "end_time": null,
            "number": 13,
            "yellow_card": 0,
            "red_card": 0,
            "injured": false,
            "goal": 0,
            "own_goal": 0,
            "playing_time": {
                "total": {
                    "minutes_tip": 25.53,
                    "minutes_otip": 25.04,
                    "start_frame": 10,
                    "end_frame": 58399,
                    "minutes_played": 97.3,
                    "minutes_played_regular_time": 97.3
                },
                "by_period": [
                    {
                        "name": "period_1",
                        "minutes_tip": 12.34,
                        "minutes_otip": 13.76,
                        "start_frame": 10,
                        "end_frame": 28900,
                        "minutes_played": 48.15
                    },
                    {
                        "name": "period_2",
                        "minutes_tip": 13.19,
                        "minutes_otip": 11.28,
                        "start_frame": 28910,
                        "end_frame": 58399,
                        "minutes_played": 49.15
                    }
                ]
            },
            "team_player_id": 1495575,
            "team_id": 2902,
            "id": 957034,
            "first_name": "Dean",
            "last_name": "Pelekanos",
            "short_name": "D. Pelekanos",
            "birthday": "2001-01-05",
            "trackable_object": 958597,
            "gender": "male"
        },
        {
            "player_role": {
                "id": 4,
                "position_group": "Central Defender",
                "name": "Right Center Back",
                "acronym": "RCB"
            },
            "start_time": "00:00:00",
            "end_time": null,
            "number": 3,
            "yellow_card": 0,
            "red_card": 0,
            "injured": false,
            "goal": 0,
            "own_goal": 0,
            "playing_time": {
                "total": {
                    "minutes_tip": 25.04,
                    "minutes_otip": 25.53,
                    "start_frame": 10,
                    "end_frame": 58399,
                    "minutes_played": 97.3,
                    "minutes_played_regular_time": 97.3
                },
                "by_period": [
                    {
                        "name": "period_1",
                        "minutes_tip": 13.76,
                        "minutes_otip": 12.34,
                        "start_frame": 10,
                        "end_frame": 28900,
                        "minutes_played": 48.15
                    },
                    {
                        "name": "period_2",
                        "minutes_tip": 11.28,
                        "minutes_otip": 13.19,
                        "start_frame": 28910,
                        "end_frame": 58399,
                        "minutes_played": 49.15
                    }
                ]
            },
            "team_player_id": 1204880,
            "team_id": 870,
            "id": 795510,
            "first_name": "Brian",
            "last_name": "Kaltak",
            "short_name": "B. Kaltak",
            "birthday": "1993-09-30",
            "trackable_object": 797073,
            "gender": "male"
        },
        {
            "player_role": {
                "id": 15,
                "position_group": "Center Forward",
                "name": "Center Forward",
                "acronym": "CF"
            },
            "start_time": "01:14:22",
            "end_time": null,
            "number": 35,
            "yellow_card": 0,
            "red_card": 0,
            "injured": false,
            "goal": 0,
            "own_goal": 0,
            "playing_time": {
                "total": {
                    "minutes_tip": 5.31,
                    "minutes_otip": 7.14,
                    "start_frame": 46530,
                    "end_frame": 58399,
                    "minutes_played": 19.78,
                    "minutes_played_regular_time": 19.78
                },
                "by_period": [
                    {
                        "name": "period_2",
                        "minutes_tip": 5.31,
                        "minutes_otip": 7.14,
                        "start_frame": 46530,
                        "end_frame": 58399,
                        "minutes_played": 19.78
                    }
                ]
            },
            "team_player_id": 1448860,
            "team_id": 870,
            "id": 923865,
            "first_name": "Arthur",
            "last_name": "De Lima",
            "short_name": "A. De Lima",
            "birthday": null,
            "trackable_object": 925428,
            "gender": "male"
        },
        {
            "player_role": {
                "id": 12,
                "position_group": "Wide Attacker",
                "name": "Left Winger",
                "acronym": "LW"
            },
            "start_time": "00:00:00",
            "end_time": null,
            "number": 10,
            "yellow_card": 0,
            "red_card": 0,
            "injured": false,
            "goal": 0,
            "own_goal": 0,
            "playing_time": {
                "total": {
                    "minutes_tip": 25.04,
                    "minutes_otip": 25.53,
                    "start_frame": 10,
                    "end_frame": 58399,
                    "minutes_played": 97.3,
                    "minutes_played_regular_time": 97.3
                },
                "by_period": [
                    {
                        "name": "period_1",
                        "minutes_tip": 13.76,
                        "minutes_otip": 12.34,
                        "start_frame": 10,
                        "end_frame": 28900,
                        "minutes_played": 48.15
                    },
                    {
                        "name": "period_2",
                        "minutes_tip": 11.28,
                        "minutes_otip": 13.19,
                        "start_frame": 28910,
                        "end_frame": 58399,
                        "minutes_played": 49.15
                    }
                ]
            },
            "team_player_id": 1204879,
            "team_id": 870,
            "id": 34423,
            "first_name": "Antonio Mikael",
            "last_name": "Rodrigues Brito",
            "short_name": "Mikael Doka",
            "birthday": "2000-01-24",
            "trackable_object": 35534,
            "gender": "male"
        },
        {
            "player_role": {
                "id": 13,
                "position_group": "Wide Attacker",
                "name": "Right Winger",
                "acronym": "RW"
            },
            "start_time": "01:14:36",
            "end_time": null,
            "number": 64,
            "yellow_card": 0,
            "red_card": 0,
            "injured": false,
            "goal": 0,
            "own_goal": 0,
            "playing_time": {
                "total": {
                    "minutes_tip": 7.14,
                    "minutes_otip": 5.31,
                    "start_frame": 46670,
                    "end_frame": 58399,
                    "minutes_played": 19.55,
                    "minutes_played_regular_time": 19.55
                },
                "by_period": [
                    {
                        "name": "period_2",
                        "minutes_tip": 7.14,
                        "minutes_otip": 5.31,
                        "start_frame": 46670,
                        "end_frame": 58399,
                        "minutes_played": 19.55
                    }
                ]
            },
            "team_player_id": 1495576,
            "team_id": 2902,
            "id": 5521,
            "first_name": "Juan Manuel",
            "last_name": "Mata García",
            "short_name": "Juan Mata",
            "birthday": "1988-04-28",
            "trackable_object": 5531,
            "gender": "male"
        },
        {
            "player_role": {
                "id": 9,
                "position_group": "Midfield",
                "name": "Left Midfield",
                "acronym": "LM"
            },
            "start_time": "00:00:00",
            "end_time": "01:04:21",
            "number": 18,
            "yellow_card": 0,
            "red_card": 0,
            "injured": false,
            "goal": 0,
            "own_goal": 0,
            "playing_time": {
                "total": {
                    "minutes_tip": 16.3,
                    "minutes_otip": 17.74,
                    "start_frame": 10,
                    "end_frame": 40519,
                    "minutes_played": 67.5,
                    "minutes_played_regular_time": 67.5
                },
                "by_period": [
                    {
                        "name": "period_1",
                        "minutes_tip": 12.34,
                        "minutes_otip": 13.76,
                        "start_frame": 10,
                        "end_frame": 28900,
                        "minutes_played": 48.15
                    },
                    {
                        "name": "period_2",
                        "minutes_tip": 3.96,
                        "minutes_otip": 3.98,
                        "start_frame": 28910,
                        "end_frame": 40519,
                        "minutes_played": 19.35
                    }
                ]
            },
            "team_player_id": 1204911,
            "team_id": 2902,
            "id": 795525,
            "first_name": "Oscar James",
            "last_name": "Moncrieff Priestman",
            "short_name": "O. Priestman",
            "birthday": "2003-03-25",
            "trackable_object": 797088,
            "gender": "male"
        },
        {
            "player_role": {
                "id": 12,
                "position_group": "Wide Attacker",
                "name": "Left Winger",
                "acronym": "LW"
            },
            "start_time": "00:00:00",
            "end_time": null,
            "number": 23,
            "yellow_card": 0,
            "red_card": 0,
            "injured": false,
            "goal": 0,
            "own_goal": 0,
            "playing_time": {
                "total": {
                    "minutes_tip": 25.53,
                    "minutes_otip": 25.04,
                    "start_frame": 10,
                    "end_frame": 58399,
                    "minutes_played": 97.3,
                    "minutes_played_regular_time": 97.3
                },
                "by_period": [
                    {
                        "name": "period_1",
                        "minutes_tip": 12.34,
                        "minutes_otip": 13.76,
                        "start_frame": 10,
                        "end_frame": 28900,
                        "minutes_played": 48.15
                    },
                    {
                        "name": "period_2",
                        "minutes_tip": 13.19,
                        "minutes_otip": 11.28,
                        "start_frame": 28910,
                        "end_frame": 58399,
                        "minutes_played": 49.15
                    }
                ]
            },
            "team_player_id": 1495574,
            "team_id": 2902,
            "id": 13542,
            "first_name": "Bozhidar",
            "last_name": "Kraev",
            "short_name": "B. Kraev",
            "birthday": "1997-06-23",
            "trackable_object": 13739,
            "gender": "male"
        },
        {
            "player_role": {
                "id": 19,
                "position_group": "Full Back",
                "name": "Left Back",
                "acronym": "LB"
            },
            "start_time": "01:27:49",
            "end_time": null,
            "number": 3,
            "yellow_card": 0,
            "red_card": 0,
            "injured": false,
            "goal": 0,
            "own_goal": 0,
            "playing_time": {
                "total": {
                    "minutes_tip": 2.17,
                    "minutes_otip": 1.57,
                    "start_frame": 54600,
                    "end_frame": 58399,
                    "minutes_played": 6.33,
                    "minutes_played_regular_time": 6.33
                },
                "by_period": [
                    {
                        "name": "period_2",
                        "minutes_tip": 2.17,
                        "minutes_otip": 1.57,
                        "start_frame": 54600,
                        "end_frame": 58399,
                        "minutes_played": 6.33
                    }
                ]
            },
            "team_player_id": 1541519,
            "team_id": 2902,
            "id": 13244,
            "first_name": "Alex",
            "last_name": "Gersbach",
            "short_name": "A. Gersbach",
            "birthday": "1997-05-08",
            "trackable_object": 13429,
            "gender": "male"
        },
        {
            "player_role": {
                "id": 15,
                "position_group": "Center Forward",
                "name": "Center Forward",
                "acronym": "CF"
            },
            "start_time": "00:00:00",
            "end_time": "01:04:21",
            "number": 7,
            "yellow_card": 0,
            "red_card": 0,
            "injured": false,
            "goal": 1,
            "own_goal": 0,
            "playing_time": {
                "total": {
                    "minutes_tip": 16.3,
                    "minutes_otip": 17.74,
                    "start_frame": 10,
                    "end_frame": 40519,
                    "minutes_played": 67.5,
                    "minutes_played_regular_time": 67.5
                },
                "by_period": [
                    {
                        "name": "period_1",
                        "minutes_tip": 12.34,
                        "minutes_otip": 13.76,
                        "start_frame": 10,
                        "end_frame": 28900,
                        "minutes_played": 48.15
                    },
                    {
                        "name": "period_2",
                        "minutes_tip": 3.96,
                        "minutes_otip": 3.98,
                        "start_frame": 28910,
                        "end_frame": 40519,
                        "minutes_played": 19.35
                    }
                ]
            },
            "team_player_id": 1204912,
            "team_id": 2902,
            "id": 795526,
            "first_name": "Zachary",
            "last_name": "Sapsford",
            "short_name": "Z. Sapsford",
            "birthday": "2002-08-16",
            "trackable_object": 797089,
            "gender": "male"
        },
        {
            "player_role": {
                "id": 15,
                "position_group": "Center Forward",
                "name": "Center Forward",
                "acronym": "CF"
            },
            "start_time": "00:00:00",
            "end_time": "00:48:09",
            "number": 23,
            "yellow_card": 0,
            "red_card": 0,
            "injured": false,
            "goal": 0,
            "own_goal": 0,
            "playing_time": {
                "total": {
                    "minutes_tip": 13.76,
                    "minutes_otip": 12.34,
                    "start_frame": 10,
                    "end_frame": 28899,
                    "minutes_played": 48.15,
                    "minutes_played_regular_time": 48.15
                },
                "by_period": [
                    {
                        "name": "period_1",
                        "minutes_tip": 13.76,
                        "minutes_otip": 12.34,
                        "start_frame": 10,
                        "end_frame": 28899,
                        "minutes_played": 48.15
                    }
                ]
            },
            "team_player_id": 1204888,
            "team_id": 870,
            "id": 795514,
            "first_name": "Miguel",
            "last_name": "Di Pizio",
            "short_name": "M. Di Pizio",
            "birthday": "2006-01-04",
            "trackable_object": 797077,
            "gender": "male"
        },
        {
            "player_role": {
                "id": 19,
                "position_group": "Full Back",
                "name": "Left Back",
                "acronym": "LB"
            },
            "start_time": "00:00:00",
            "end_time": null,
            "number": 12,
            "yellow_card": 0,
            "red_card": 0,
            "injured": false,
            "goal": 0,
            "own_goal": 0,
            "playing_time": {
                "total": {
                    "minutes_tip": 25.04,
                    "minutes_otip": 25.53,
                    "start_frame": 10,
                    "end_frame": 58399,
                    "minutes_played": 97.3,
                    "minutes_played_regular_time": 97.3
                },
                "by_period": [
                    {
                        "name": "period_1",
                        "minutes_tip": 13.76,
                        "minutes_otip": 12.34,
                        "start_frame": 10,
                        "end_frame": 28900,
                        "minutes_played": 48.15
                    },
                    {
                        "name": "period_2",
                        "minutes_tip": 11.28,
                        "minutes_otip": 13.19,
                        "start_frame": 28910,
                        "end_frame": 58399,
                        "minutes_played": 49.15
                    }
                ]
            },
            "team_player_id": 1448855,
            "team_id": 870,
            "id": 51683,
            "first_name": "Lucas",
            "last_name": "Mauragis",
            "short_name": "L. Mauragis",
            "birthday": "2001-09-04",
            "trackable_object": 52809,
            "gender": "male"
        },
        {
            "player_role": {
                "id": 9,
                "position_group": "Midfield",
                "name": "Left Midfield",
                "acronym": "LM"
            },
            "start_time": "01:04:21",
            "end_time": null,
            "number": 6,
            "yellow_card": 0,
            "red_card": 0,
            "injured": false,
            "goal": 0,
            "own_goal": 0,
            "playing_time": {
                "total": {
                    "minutes_tip": 9.23,
                    "minutes_otip": 7.3,
                    "start_frame": 40520,
                    "end_frame": 58399,
                    "minutes_played": 29.8,
                    "minutes_played_regular_time": 29.8
                },
                "by_period": [
                    {
                        "name": "period_2",
                        "minutes_tip": 9.23,
                        "minutes_otip": 7.3,
                        "start_frame": 40520,
                        "end_frame": 58399,
                        "minutes_played": 29.8
                    }
                ]
            },
            "team_player_id": 1554863,
            "team_id": 2902,
            "id": 735576,
            "first_name": "Mohamed",
            "last_name": "Al-Taay",
            "short_name": "M. Al-Taay",
            "birthday": "2000-06-15",
            "trackable_object": 737139,
            "gender": "male"
        },
        {
            "player_role": {
                "id": 15,
                "position_group": "Center Forward",
                "name": "Center Forward",
                "acronym": "CF"
            },
            "start_time": "00:00:00",
            "end_time": "01:14:22",
            "number": 9,
            "yellow_card": 0,
            "red_card": 0,
            "injured": false,
            "goal": 0,
            "own_goal": 0,
            "playing_time": {
                "total": {
                    "minutes_tip": 19.73,
                    "minutes_otip": 18.4,
                    "start_frame": 10,
                    "end_frame": 46529,
                    "minutes_played": 77.52,
                    "minutes_played_regular_time": 77.52
                },
                "by_period": [
                    {
                        "name": "period_1",
                        "minutes_tip": 13.76,
                        "minutes_otip": 12.34,
                        "start_frame": 10,
                        "end_frame": 28900,
                        "minutes_played": 48.15
                    },
                    {
                        "name": "period_2",
                        "minutes_tip": 5.97,
                        "minutes_otip": 6.05,
                        "start_frame": 28910,
                        "end_frame": 46529,
                        "minutes_played": 29.36
                    }
                ]
            },
            "team_player_id": 74034,
            "team_id": 870,
            "id": 51668,
            "first_name": "Alou",
            "last_name": "Kuol",
            "short_name": "A. Kuol",
            "birthday": "2001-07-05",
            "trackable_object": 52794,
            "gender": "male"
        },
        {
            "player_role": {
                "id": 20,
                "position_group": "Full Back",
                "name": "Right Back",
                "acronym": "RB"
            },
            "start_time": "00:00:00",
            "end_time": null,
            "number": 2,
            "yellow_card": 0,
            "red_card": 0,
            "injured": false,
            "goal": 0,
            "own_goal": 0,
            "playing_time": {
                "total": {
                    "minutes_tip": 25.53,
                    "minutes_otip": 25.04,
                    "start_frame": 10,
                    "end_frame": 58399,
                    "minutes_played": 97.3,
                    "minutes_played_regular_time": 97.3
                },
                "by_period": [
                    {
                        "name": "period_1",
                        "minutes_tip": 12.34,
                        "minutes_otip": 13.76,
                        "start_frame": 10,
                        "end_frame": 28900,
                        "minutes_played": 48.15
                    },
                    {
                        "name": "period_2",
                        "minutes_tip": 13.19,
                        "minutes_otip": 11.28,
                        "start_frame": 28910,
                        "end_frame": 58399,
                        "minutes_played": 49.15
                    }
                ]
            },
            "team_player_id": 1219775,
            "team_id": 2902,
            "id": 33430,
            "first_name": "Gabriel",
            "last_name": "Cléùr",
            "short_name": "G. Cléùr",
            "birthday": "1998-01-31",
            "trackable_object": 34538,
            "gender": "male"
        },
        {
            "player_role": {
                "id": 3,
                "position_group": "Central Defender",
                "name": "Left Center Back",
                "acronym": "LCB"
            },
            "start_time": "00:00:00",
            "end_time": "00:48:09",
            "number": 33,
            "yellow_card": 0,
            "red_card": 0,
            "injured": false,
            "goal": 0,
            "own_goal": 0,
            "playing_time": {
                "total": {
                    "minutes_tip": 13.76,
                    "minutes_otip": 12.34,
                    "start_frame": 10,
                    "end_frame": 28899,
                    "minutes_played": 48.15,
                    "minutes_played_regular_time": 48.15
                },
                "by_period": [
                    {
                        "name": "period_1",
                        "minutes_tip": 13.76,
                        "minutes_otip": 12.34,
                        "start_frame": 10,
                        "end_frame": 28899,
                        "minutes_played": 48.15
                    }
                ]
            },
            "team_player_id": 1204883,
            "team_id": 870,
            "id": 795511,
            "first_name": "Nathan",
            "last_name": "Paull",
            "short_name": "N. Paull",
            "birthday": "2003-08-21",
            "trackable_object": 797074,
            "gender": "male"
        },
        {
            "player_role": {
                "id": 13,
                "position_group": "Wide Attacker",
                "name": "Right Winger",
                "acronym": "RW"
            },
            "start_time": "00:00:00",
            "end_time": "01:14:36",
            "number": 14,
            "yellow_card": 1,
            "red_card": 0,
            "injured": false,
            "goal": 1,
            "own_goal": 0,
            "playing_time": {
                "total": {
                    "minutes_tip": 18.4,
                    "minutes_otip": 19.73,
                    "start_frame": 10,
                    "end_frame": 46669,
                    "minutes_played": 77.75,
                    "minutes_played_regular_time": 77.75
                },
                "by_period": [
                    {
                        "name": "period_1",
                        "minutes_tip": 12.34,
                        "minutes_otip": 13.76,
                        "start_frame": 10,
                        "end_frame": 28900,
                        "minutes_played": 48.15
                    },
                    {
                        "name": "period_2",
                        "minutes_tip": 6.05,
                        "minutes_otip": 5.97,
                        "start_frame": 28910,
                        "end_frame": 46669,
                        "minutes_played": 29.6
                    }
                ]
            },
            "team_player_id": 1204903,
            "team_id": 2902,
            "id": 51036,
            "first_name": "Nicolas",
            "last_name": "Milanovic",
            "short_name": "N. Milanovic",
            "birthday": "2001-11-14",
            "trackable_object": 52162,
            "gender": "male"
        },
        {
            "player_role": {
                "id": 15,
                "position_group": "Center Forward",
                "name": "Center Forward",
                "acronym": "CF"
            },
            "start_time": "00:00:00",
            "end_time": "01:27:49",
            "number": 26,
            "yellow_card": 0,
            "red_card": 0,
            "injured": false,
            "goal": 0,
            "own_goal": 0,
            "playing_time": {
                "total": {
                    "minutes_tip": 23.36,
                    "minutes_otip": 23.48,
                    "start_frame": 10,
                    "end_frame": 54599,
                    "minutes_played": 90.96,
                    "minutes_played_regular_time": 90.96
                },
                "by_period": [
                    {
                        "name": "period_1",
                        "minutes_tip": 12.34,
                        "minutes_otip": 13.76,
                        "start_frame": 10,
                        "end_frame": 28900,
                        "minutes_played": 48.15
                    },
                    {
                        "name": "period_2",
                        "minutes_tip": 11.02,
                        "minutes_otip": 9.72,
                        "start_frame": 28910,
                        "end_frame": 54599,
                        "minutes_played": 42.82
                    }
                ]
            },
            "team_player_id": 828327,
            "team_id": 2902,
            "id": 19052,
            "first_name": "Brandon",
            "last_name": "Borrello",
            "short_name": "B. Borrello",
            "birthday": "1995-07-25",
            "trackable_object": 19249,
            "gender": "male"
        },
        {
            "player_role": {
                "id": 10,
                "position_group": "Midfield",
                "name": "Right Midfield",
                "acronym": "RM"
            },
            "start_time": "00:48:09",
            "end_time": null,
            "number": 8,
            "yellow_card": 0,
            "red_card": 0,
            "injured": false,
            "goal": 0,
            "own_goal": 0,
            "playing_time": {
                "total": {
                    "minutes_tip": 11.28,
                    "minutes_otip": 13.19,
                    "start_frame": 28910,
                    "end_frame": 58399,
                    "minutes_played": 49.15,
                    "minutes_played_regular_time": 49.15
                },
                "by_period": [
                    {
                        "name": "period_2",
                        "minutes_tip": 11.28,
                        "minutes_otip": 13.19,
                        "start_frame": 28910,
                        "end_frame": 58399,
                        "minutes_played": 49.15
                    }
                ]
            },
            "team_player_id": 1448852,
            "team_id": 870,
            "id": 29856,
            "first_name": "Alfie",
            "last_name": "McCalmont",
            "short_name": "A. McCalmont",
            "birthday": "2000-03-25",
            "trackable_object": 30949,
            "gender": "male"
        },
        {
            "player_role": {
                "id": 17,
                "position_group": "Other",
                "name": "Substitute",
                "acronym": "SUB"
            },
            "start_time": null,
            "end_time": null,
            "number": 30,
            "yellow_card": 0,
            "red_card": 0,
            "injured": false,
            "goal": 0,
            "own_goal": 0,
            "playing_time": {
                "total": null,
                "by_period": []
            },
            "team_player_id": 1495572,
            "team_id": 2902,
            "id": 14043,
            "first_name": "Jordan",
            "last_name": "Holmes",
            "short_name": "J. Holmes",
            "birthday": "1997-05-08",
            "trackable_object": 14240,
            "gender": "male"
        },
        {
            "player_role": {
                "id": 17,
                "position_group": "Other",
                "name": "Substitute",
                "acronym": "SUB"
            },
            "start_time": null,
            "end_time": null,
            "number": 17,
            "yellow_card": 0,
            "red_card": 0,
            "injured": false,
            "goal": 0,
            "own_goal": 0,
            "playing_time": {
                "total": null,
                "by_period": []
            },
            "team_player_id": 1520603,
            "team_id": 2902,
            "id": 795533,
            "first_name": "Jarrod",
            "last_name": "Carluccio",
            "short_name": "J. Carluccio",
            "birthday": "2001-02-08",
            "trackable_object": 797096,
            "gender": "male"
        },
        {
            "player_role": {
                "id": 0,
                "position_group": "Other",
                "name": "Goalkeeper",
                "acronym": "GK"
            },
            "start_time": "00:00:00",
            "end_time": null,
            "number": 20,
            "yellow_card": 0,
            "red_card": 0,
            "injured": false,
            "goal": 0,
            "own_goal": 0,
            "playing_time": {
                "total": {
                    "minutes_tip": 25.53,
                    "minutes_otip": 25.04,
                    "start_frame": 10,
                    "end_frame": 58399,
                    "minutes_played": 97.3,
                    "minutes_played_regular_time": 97.3
                },
                "by_period": [
                    {
                        "name": "period_1",
                        "minutes_tip": 12.34,
                        "minutes_otip": 13.76,
                        "start_frame": 10,
                        "end_frame": 28900,
                        "minutes_played": 48.15
                    },
                    {
                        "name": "period_2",
                        "minutes_tip": 13.19,
                        "minutes_otip": 11.28,
                        "start_frame": 28910,
                        "end_frame": 58399,
                        "minutes_played": 49.15
                    }
                ]
            },
            "team_player_id": 828330,
            "team_id": 2902,
            "id": 23885,
            "first_name": "Lawrence ",
            "last_name": "Thomas",
            "short_name": "L. Thomas",
            "birthday": "1992-05-09",
            "trackable_object": 24842,
            "gender": "male"
        },
        {
            "player_role": {
                "id": 4,
                "position_group": "Central Defender",
                "name": "Right Center Back",
                "acronym": "RCB"
            },
            "start_time": "00:00:00",
            "end_time": null,
            "number": 22,
            "yellow_card": 1,
            "red_card": 0,
            "injured": false,
            "goal": 0,
            "own_goal": 0,
            "playing_time": {
                "total": {
                    "minutes_tip": 25.53,
                    "minutes_otip": 25.04,
                    "start_frame": 10,
                    "end_frame": 58399,
                    "minutes_played": 97.3,
                    "minutes_played_regular_time": 97.3
                },
                "by_period": [
                    {
                        "name": "period_1",
                        "minutes_tip": 12.34,
                        "minutes_otip": 13.76,
                        "start_frame": 10,
                        "end_frame": 28900,
                        "minutes_played": 48.15
                    },
                    {
                        "name": "period_2",
                        "minutes_tip": 13.19,
                        "minutes_otip": 11.28,
                        "start_frame": 28910,
                        "end_frame": 58399,
                        "minutes_played": 49.15
                    }
                ]
            },
            "team_player_id": 1204908,
            "team_id": 2902,
            "id": 795523,
            "first_name": "Anthony",
            "last_name": "Pantazopoulos",
            "short_name": "A. Pantazopoulos",
            "birthday": "2003-04-22",
            "trackable_object": 797086,
            "gender": "male"
        },
        {
            "player_role": {
                "id": 3,
                "position_group": "Central Defender",
                "name": "Left Center Back",
                "acronym": "LCB"
            },
            "start_time": "00:00:00",
            "end_time": null,
            "number": 4,
            "yellow_card": 0,
            "red_card": 0,
            "injured": false,
            "goal": 0,
            "own_goal": 0,
            "playing_time": {
                "total": {
                    "minutes_tip": 25.53,
                    "minutes_otip": 25.04,
                    "start_frame": 10,
                    "end_frame": 58399,
                    "minutes_played": 97.3,
                    "minutes_played_regular_time": 97.3
                },
                "by_period": [
                    {
                        "name": "period_1",
                        "minutes_tip": 12.34,
                        "minutes_otip": 13.76,
                        "start_frame": 10,
                        "end_frame": 28900,
                        "minutes_played": 48.15
                    },
                    {
                        "name": "period_2",
                        "minutes_tip": 13.19,
                        "minutes_otip": 11.28,
                        "start_frame": 28910,
                        "end_frame": 58399,
                        "minutes_played": 49.15
                    }
                ]
            },
            "team_player_id": 828334,
            "team_id": 2902,
            "id": 560990,
            "first_name": "Alex",
            "last_name": "Bonetig",
            "short_name": "A. Bonetig",
            "birthday": "2002-08-20",
            "trackable_object": 562547,
            "gender": "male"
        },
        {
            "player_role": {
                "id": 17,
                "position_group": "Other",
                "name": "Substitute",
                "acronym": "SUB"
            },
            "start_time": null,
            "end_time": null,
            "number": 40,
            "yellow_card": 0,
            "red_card": 0,
            "injured": false,
            "goal": 0,
            "own_goal": 0,
            "playing_time": {
                "total": null,
                "by_period": []
            },
            "team_player_id": 1448857,
            "team_id": 870,
            "id": 923862,
            "first_name": "Dylan",
            "last_name": "Peraic-Cullen",
            "short_name": "D. Peraic-Cullen",
            "birthday": "2006-07-25",
            "trackable_object": 925425,
            "gender": "male"
        },
        {
            "player_role": {
                "id": 17,
                "position_group": "Other",
                "name": "Substitute",
                "acronym": "SUB"
            },
            "start_time": null,
            "end_time": null,
            "number": 24,
            "yellow_card": 0,
            "red_card": 0,
            "injured": false,
            "goal": 0,
            "own_goal": 0,
            "playing_time": {
                "total": null,
                "by_period": []
            },
            "team_player_id": 1448856,
            "team_id": 870,
            "id": 330380,
            "first_name": "Diesel",
            "last_name": "Herrington",
            "short_name": "D. Herrington",
            "birthday": "2004-08-04",
            "trackable_object": 331937,
            "gender": "male"
        },
        {
            "player_role": {
                "id": 20,
                "position_group": "Full Back",
                "name": "Right Back",
                "acronym": "RB"
            },
            "start_time": "00:00:00",
            "end_time": null,
            "number": 4,
            "yellow_card": 1,
            "red_card": 0,
            "injured": false,
            "goal": 0,
            "own_goal": 0,
            "playing_time": {
                "total": {
                    "minutes_tip": 25.04,
                    "minutes_otip": 25.53,
                    "start_frame": 10,
                    "end_frame": 58399,
                    "minutes_played": 97.3,
                    "minutes_played_regular_time": 97.3
                },
                "by_period": [
                    {
                        "name": "period_1",
                        "minutes_tip": 13.76,
                        "minutes_otip": 12.34,
                        "start_frame": 10,
                        "end_frame": 28900,
                        "minutes_played": 48.15
                    },
                    {
                        "name": "period_2",
                        "minutes_tip": 11.28,
                        "minutes_otip": 13.19,
                        "start_frame": 28910,
                        "end_frame": 58399,
                        "minutes_played": 49.15
                    }
                ]
            },
            "team_player_id": 1448850,
            "team_id": 870,
            "id": 10549,
            "first_name": "Trent",
            "last_name": "Sainsbury",
            "short_name": "T. Sainsbury",
            "birthday": "1992-01-05",
            "trackable_object": 10559,
            "gender": "male"
        },
        {
            "player_role": {
                "id": 0,
                "position_group": "Other",
                "name": "Goalkeeper",
                "acronym": "GK"
            },
            "start_time": "00:00:00",
            "end_time": null,
            "number": 1,
            "yellow_card": 0,
            "red_card": 0,
            "injured": false,
            "goal": 0,
            "own_goal": 0,
            "playing_time": {
                "total": {
                    "minutes_tip": 25.04,
                    "minutes_otip": 25.53,
                    "start_frame": 10,
                    "end_frame": 58399,
                    "minutes_played": 97.3,
                    "minutes_played_regular_time": 97.3
                },
                "by_period": [
                    {
                        "name": "period_1",
                        "minutes_tip": 13.76,
                        "minutes_otip": 12.34,
                        "start_frame": 10,
                        "end_frame": 28900,
                        "minutes_played": 48.15
                    },
                    {
                        "name": "period_2",
                        "minutes_tip": 11.28,
                        "minutes_otip": 13.19,
                        "start_frame": 28910,
                        "end_frame": 58399,
                        "minutes_played": 49.15
                    }
                ]
            },
            "team_player_id": 1448853,
            "team_id": 870,
            "id": 152947,
            "first_name": "Adam",
            "last_name": "Pavlesic",
            "short_name": "A. Pavlesic",
            "birthday": "2002-07-30",
            "trackable_object": 154502,
            "gender": "male"
        }
    ],
    "status": "closed",
    "home_team_side": [
        "right_to_left",
        "left_to_right"
    ],
    "ball": {
        "trackable_object": 55
    },
    "pitch_length": 105,
    "pitch_width": 68
}